tidypyspark/__init__.py
tidypyspark/_unexported_utils.py
tidypyspark/accessor_class.py
tidypyspark/data/__init__.py
tidypyspark/data/pen.csv
tidypyspark/datasets.py
tidypyspark/tidypyspark_class.py
tidypyspark-0.0.1.dist-info/LICENSE
tidypyspark-0.0.1.dist-info/METADATA
tidypyspark-0.0.1.dist-info/WHEEL
tidypyspark-0.0.1.dist-info/RECORD
