Metadata-Version: 2.1
Name: tidypyspark
Version: 0.0.1
Summary: dplyr for pyspark
License: GNU General Public License v3.0
Author: Srikanth Komala sheshachala
Requires-Python: >=3.8,<4.0
Classifier: License :: Other/Proprietary License
Classifier: Programming Language :: Python :: 3
Classifier: Programming Language :: Python :: 3.8
Classifier: Programming Language :: Python :: 3.9
Classifier: Programming Language :: Python :: 3.10
Classifier: Programming Language :: Python :: 3.11
Requires-Dist: collections-extended (>=2.0.2,<3.0.0)
Requires-Dist: numpy (>=1.24.2,<2.0.0)
Requires-Dist: pandas (>=1.0.0,<2.0.0)
Requires-Dist: pyspark (>=3.3.1,<4.0.0)
